sbxpy/QueryBuilder.py
sbxpy/__init__.py
sbxpy/cache/__init__.py
sbxpy/domain/__init__.py
sbxpy/sbx/__init__.py
sbxpy/service/__init__.py
sbxpy-0.8.1.dist-info/licenses/LICENSE
sbxpy-0.8.1.dist-info/METADATA
sbxpy-0.8.1.dist-info/WHEEL
sbxpy-0.8.1.dist-info/top_level.txt
sbxpy-0.8.1.dist-info/RECORD
