Metadata-Version: 2.4
Name: sbxpy
Version: 0.8.1
Summary: Add your description here
Home-page: https://github.com/sbxcloud/sbxcloudpython
Author: Luis Guzmán
Author-email: lgguzman890414@gmail.com
Requires-Python: >=3.12
License-File: LICENSE
Requires-Dist: aiohttp>=3.7.3
Requires-Dist: pydantic>=2.1.0
Requires-Dist: redis>=4.5.2
Dynamic: author
Dynamic: author-email
Dynamic: home-page
Dynamic: license-file
